.gitignore
.travis.yml
AUTHORS.rst
CHANGELOG.rst
Dockerfile
LICENSE
MANIFEST.in
Makefile
README.rst
docker-compose.yml
setup.cfg
setup.py
bin/docker-entrypoint
bin/wait-for-it.sh
src/emtwo_extensions.egg-info/PKG-INFO
src/emtwo_extensions.egg-info/SOURCES.txt
src/emtwo_extensions.egg-info/dependency_links.txt
src/emtwo_extensions.egg-info/entry_points.txt
src/emtwo_extensions.egg-info/not-zip-safe
src/emtwo_extensions.egg-info/requires.txt
src/emtwo_extensions.egg-info/top_level.txt
src/redash_stmo/__init__.py
src/redash_stmo/dockerflow.py
src/redash_stmo/resources.py
src/redash_stmo/settings.py
src/redash_stmo/data_sources/__init__.py
src/redash_stmo/data_sources/health.py
src/redash_stmo/data_sources/link/__init__.py
src/redash_stmo/data_sources/link/bundle/datasource_link.js
src/redash_stmo/data_sources/version/__init__.py
src/redash_stmo/data_sources/version/bundle/datasource_version.js
src/redash_stmo/query_runner/__init__.py
src/redash_stmo/query_runner/activedata.py
tests/test_datasource_link.py
tests/test_datasource_version.py
tests/test_health.py