Metadata-Version: 1.1
Name: emtwo-extensions
Version: 0.0.129
Summary: Extensions to Redash by Mozilla
Home-page: https://github.com/mozilla/redash-stmo
Author: Mozilla Foundation
Author-email: dev-webdev@lists.mozilla.org
License: MPL 2.0
Platform: UNKNOWN
Classifier: Development Status :: 5 - Production/Stable
Classifier: Environment :: Web Environment :: Mozilla
Classifier: Framework :: Django
Classifier: Intended Audience :: Developers
Classifier: License :: OSI Approved :: Mozilla Public License 2.0 (MPL 2.0)
Classifier: Programming Language :: Python
Classifier: Programming Language :: Python :: 2
Classifier: Programming Language :: Python :: 2.7
Classifier: Programming Language :: Python :: 3
Classifier: Programming Language :: Python :: 3.4
Classifier: Programming Language :: Python :: 3.5
Classifier: Programming Language :: Python :: 3.6
Classifier: Topic :: Internet :: WWW/HTTP
